postDB/__init__.py
postDB/exceptions.py
postDB/types.py
postDB/model/__init__.py
postDB/model/column.py
postDB/model/index.py
postDB/model/meta.py
postDB/model/model.py
postDB-0.3.0.dist-info/LICENSE
postDB-0.3.0.dist-info/METADATA
postDB-0.3.0.dist-info/WHEEL
postDB-0.3.0.dist-info/top_level.txt
postDB-0.3.0.dist-info/RECORD
