Metadata-Version: 2.1
Name: postDB
Version: 0.3.0
Summary: A WIP asynchronous database module for PostgreSQL databases.
Home-page: https://github.com/SylteA/postDB
Author: Sylte
Project-URL: Bug Tracker, https://github.com/SylteA/postDB/issues
Project-URL: Codebase, https://github.com/SylteA/postDB
Classifier: Programming Language :: Python :: 3.6
Classifier: License :: OSI Approved :: MIT License
Classifier: Development Status :: 3 - Alpha
Classifier: Intended Audience :: Developers
Classifier: Natural Language :: English
Requires-Python: >=3.6
License-File: LICENSE
Requires-Dist: asyncpg
Provides-Extra: dev
Requires-Dist: black ; extra == 'dev'
